symbulate/__init__.py
symbulate/base.py
symbulate/distributions.py
symbulate/gaussian_process.py
symbulate/independence.py
symbulate/index_sets.py
symbulate/markov_chains.py
symbulate/math.py
symbulate/options.py
symbulate/plot.py
symbulate/poisson_process.py
symbulate/probability_space.py
symbulate/random_processes.py
symbulate/random_variables.py
symbulate/result.py
symbulate/results.py
symbulate/seed.py
symbulate/sequences.py
symbulate/table.py
symbulate/time_index.py
symbulate/utils.py
symbulate/vectors.py
symbulate/tests/__init__.py
symbulate/tests/test_distributions.py
symbulate-0.5.7.dist-info/LICENSE.txt
symbulate-0.5.7.dist-info/METADATA
symbulate-0.5.7.dist-info/WHEEL
symbulate-0.5.7.dist-info/top_level.txt
symbulate-0.5.7.dist-info/RECORD
