Metadata-Version: 2.1
Name: symbulate
Version: 0.5.7
Summary: A symbolic algebra for specifying simulations.
Home-page: https://github.com/dlsun/symbulate
Author: Dennis Sun
Author-email: dsun09@calpoly.edu
License: GPLv3
Keywords: probability simulation
Platform: UNKNOWN
Classifier: Development Status :: 3 - Alpha
Classifier: Intended Audience :: Education
Classifier: Topic :: Scientific/Engineering :: Mathematics
Classifier: License :: OSI Approved :: GNU General Public License v3 (GPLv3)
Classifier: Programming Language :: Python :: 3
Requires-Dist: numpy
Requires-Dist: scipy
Requires-Dist: matplotlib
